libpyrite/__init__.py
libpyrite/harness/__init__.py
libpyrite/harness/_utils.py
libpyrite/harness/callbacks.py
libpyrite/harness/harness.py
libpyrite/harness/metrics.py
libpyrite/nn/__init__.py
libpyrite/nn/functional.py
libpyrite/nn/modules/__init__.py
libpyrite/nn/modules/dynamic_view.py
libpyrite/optim/__init__.py
libpyrite/optim/lr_scheduler.py
libpyrite/utils/__init__.py
libpyrite/utils/data/__init__.py
libpyrite/utils/data/dataloader.py
libpyrite/utils/data/dataset.py
libpyrite/utils/data/generator.py
libpyrite/version.py
libpyrite-0.1.0a1.dist-info/LICENSE
libpyrite-0.1.0a1.dist-info/WHEEL
libpyrite-0.1.0a1.dist-info/METADATA
libpyrite-0.1.0a1.dist-info/RECORD
