Metadata-Version: 2.1
Name: libpyrite
Version: 0.1.0a1
Summary: PyTorch utility library
License: Apache-2.0
Author: Miller Wilt
Author-email: miller@pyriteai.com
Requires-Python: >=3.5,<4.0
Classifier: License :: OSI Approved :: Apache Software License
Classifier: Programming Language :: Python :: 3
Classifier: Programming Language :: Python :: 3.5
Classifier: Programming Language :: Python :: 3.6
Classifier: Programming Language :: Python :: 3.7
Requires-Dist: scipy (>=1.3,<2.0)
Requires-Dist: torch (>=1.1,<2.0)
Requires-Dist: torchvision (>=0.3.0,<0.4.0)
Requires-Dist: tqdm (>=4.32,<5.0)
